LICENSE
mongodm/__init__.py
mongodm/mongo.py
mongodm/query.py
mongodm/types.py
mongodm/utils.py
mongodm-0.1.5.dist-info/LICENSE
mongodm-0.1.5.dist-info/WHEEL
mongodm-0.1.5.dist-info/METADATA
mongodm-0.1.5.dist-info/RECORD
