Metadata-Version: 2.1
Name: mongodm
Version: 0.1.5
Summary: Simple ODM for MongoDB
Home-page: https://github.com/azureswastika/mongodm
License: MIT
Keywords: odm,mongo,mongodb
Author: Deni
Author-email: azureswastika@gmail.com
Requires-Python: >=3.9,<4.0
Classifier: Development Status :: 2 - Pre-Alpha
Classifier: License :: OSI Approved :: MIT License
Classifier: Operating System :: OS Independent
Classifier: Programming Language :: Python :: 3
Classifier: Programming Language :: Python :: 3 :: Only
Classifier: Programming Language :: Python :: 3.7
Classifier: Programming Language :: Python :: 3.8
Classifier: Programming Language :: Python :: 3.9
Classifier: Topic :: Database
Classifier: Typing :: Typed
Requires-Dist: pydantic (>=1.8.2,<2.0.0)
Requires-Dist: pymongo (>=3.12.0,<4.0.0)
Project-URL: Repository, https://github.com/azureswastika/mongodm
Project-URL: issues, https://github.com/azureswastika/mongodm/issues
